flaskdeploy/__init__.py
flaskdeploy/__main__.py
flaskdeploy/config.py
flaskdeploy/run.py
flaskdeploy/run_proto.py
flaskdeploy/test.py
flaskdeploy/utils.py
flaskdeploy/validation.py
flaskdeploy/__pycache__/__init__.cpython-36.pyc
flaskdeploy/__pycache__/__main__.cpython-36.pyc
flaskdeploy/data/AppendRc.txt
flaskdeploy/data/docker_config.run
flaskdeploy/data/multi_ssl.sh
flaskdeploy/data/nginx_config.conf
flaskdeploy/data/ssl_script.sh
flaskdeploy/data/systemd_script.service
flaskdeploy/data/uwsgi_config.ini
flaskdeploy/scripts/__init__.py
flaskdeploy/scripts/core.py
flaskdeploy/scripts/deploy.py
flaskdeploy/scripts/dns(drop).py
flaskdeploy/scripts/dns.py
flaskdeploy/scripts/generation.py
flaskdeploy/scripts/run.py
flask_deploy-0.4.3.dist-info/LICENSE
flask_deploy-0.4.3.dist-info/METADATA
flask_deploy-0.4.3.dist-info/WHEEL
flask_deploy-0.4.3.dist-info/entry_points.txt
flask_deploy-0.4.3.dist-info/top_level.txt
flask_deploy-0.4.3.dist-info/RECORD
